{
  "entrypoints": [
    "main"
  ],
  "origins": {
    "237": [
      237
    ],
    "17896441": [
      250,
      401
    ],
    "main": [
      250,
      354,
      792
    ],
    "runtime~main": [
      250,
      792,
      354
    ],
    "0e384e19": [
      976
    ],
    "2e82ce9c": [
      414
    ],
    "349d9f3b": [
      759
    ],
    "49abf8cd": [
      252
    ],
    "4df0e478": [
      495
    ],
    "4f472662": [
      270
    ],
    "5e4fa025": [
      335
    ],
    "5e95c892": [
      647
    ],
    "6772779c": [
      247
    ],
    "6dfd6766": [
      154
    ],
    "7f0a4cd2": [
      248
    ],
    "88884f83": [
      782
    ],
    "93cb48b2": [
      64
    ],
    "a7456010": [
      235
    ],
    "a7bd4aaa": [
      98
    ],
    "a94703ab": [
      250,
      48
    ],
    "aba21aa0": [
      742
    ],
    "c30d6c39": [
      456
    ],
    "c4f5d8e4": [
      634
    ],
    "c82c7672": [
      959
    ],
    "ccc79d7d": [
      113
    ],
    "e0d24761": [
      906
    ],
    "eebfa656": [
      897
    ],
    "f468a7ad": [
      40
    ],
    "fe675a51": [
      869
    ],
    "styles": [
      48,
      354,
      401,
      792,
      250
    ]
  },
  "assets": {
    "40": {
      "js": [
        {
          "file": "assets/js/f468a7ad.f7248e59.js",
          "hash": "5a455d0f8844374b",
          "publicPath": "/ur/assets/js/f468a7ad.f7248e59.js"
        }
      ]
    },
    "48": {
      "js": [
        {
          "file": "assets/js/a94703ab.6db9ba88.js",
          "hash": "1f113871f95ac20d",
          "publicPath": "/ur/assets/js/a94703ab.6db9ba88.js"
        }
      ]
    },
    "64": {
      "js": [
        {
          "file": "assets/js/93cb48b2.7a84901a.js",
          "hash": "a27deec8bc505dc8",
          "publicPath": "/ur/assets/js/93cb48b2.7a84901a.js"
        }
      ]
    },
    "98": {
      "js": [
        {
          "file": "assets/js/a7bd4aaa.86d1c94e.js",
          "hash": "40e2eb3902b96571",
          "publicPath": "/ur/assets/js/a7bd4aaa.86d1c94e.js"
        }
      ]
    },
    "113": {
      "js": [
        {
          "file": "assets/js/ccc79d7d.45c325a9.js",
          "hash": "2964790aae2b6377",
          "publicPath": "/ur/assets/js/ccc79d7d.45c325a9.js"
        }
      ]
    },
    "154": {
      "js": [
        {
          "file": "assets/js/6dfd6766.4c89ef82.js",
          "hash": "73d962045ea1e006",
          "publicPath": "/ur/assets/js/6dfd6766.4c89ef82.js"
        }
      ]
    },
    "235": {
      "js": [
        {
          "file": "assets/js/a7456010.3242529d.js",
          "hash": "a535aa5703c623b9",
          "publicPath": "/ur/assets/js/a7456010.3242529d.js"
        }
      ]
    },
    "237": {
      "js": [
        {
          "file": "assets/js/237.80f18bf6.js",
          "hash": "e1f1e2d11c98bc86",
          "publicPath": "/ur/assets/js/237.80f18bf6.js"
        }
      ]
    },
    "247": {
      "js": [
        {
          "file": "assets/js/6772779c.cc4137b7.js",
          "hash": "88106fdc4f4e69f0",
          "publicPath": "/ur/assets/js/6772779c.cc4137b7.js"
        }
      ]
    },
    "248": {
      "js": [
        {
          "file": "assets/js/7f0a4cd2.589b721d.js",
          "hash": "5294157d01a7b161",
          "publicPath": "/ur/assets/js/7f0a4cd2.589b721d.js"
        }
      ]
    },
    "250": {
      "css": [
        {
          "file": "assets/css/styles.a847b1d1.css",
          "hash": "9b9945c2c202e85f",
          "publicPath": "/ur/assets/css/styles.a847b1d1.css"
        }
      ]
    },
    "252": {
      "js": [
        {
          "file": "assets/js/49abf8cd.a812246c.js",
          "hash": "3474d6eb361741fd",
          "publicPath": "/ur/assets/js/49abf8cd.a812246c.js"
        }
      ]
    },
    "270": {
      "js": [
        {
          "file": "assets/js/4f472662.38a89704.js",
          "hash": "538087f85ca6b20b",
          "publicPath": "/ur/assets/js/4f472662.38a89704.js"
        }
      ]
    },
    "335": {
      "js": [
        {
          "file": "assets/js/5e4fa025.b9ce5fef.js",
          "hash": "2bbefc0e73773557",
          "publicPath": "/ur/assets/js/5e4fa025.b9ce5fef.js"
        }
      ]
    },
    "354": {
      "js": [
        {
          "file": "assets/js/runtime~main.a42b8d11.js",
          "hash": "5810c8902191fad3",
          "publicPath": "/ur/assets/js/runtime~main.a42b8d11.js"
        }
      ]
    },
    "401": {
      "js": [
        {
          "file": "assets/js/17896441.226578e2.js",
          "hash": "a2497541b16ad552",
          "publicPath": "/ur/assets/js/17896441.226578e2.js"
        }
      ]
    },
    "414": {
      "js": [
        {
          "file": "assets/js/2e82ce9c.4e81a7f3.js",
          "hash": "e4d8b2efcb2fc287",
          "publicPath": "/ur/assets/js/2e82ce9c.4e81a7f3.js"
        }
      ]
    },
    "456": {
      "js": [
        {
          "file": "assets/js/c30d6c39.81ada4b7.js",
          "hash": "b6d33df7bd8888b1",
          "publicPath": "/ur/assets/js/c30d6c39.81ada4b7.js"
        }
      ]
    },
    "495": {
      "js": [
        {
          "file": "assets/js/4df0e478.4240e64b.js",
          "hash": "b391aa03ca88563e",
          "publicPath": "/ur/assets/js/4df0e478.4240e64b.js"
        }
      ]
    },
    "634": {
      "js": [
        {
          "file": "assets/js/c4f5d8e4.0bbd040c.js",
          "hash": "1084a3cfc50b7e5e",
          "publicPath": "/ur/assets/js/c4f5d8e4.0bbd040c.js"
        }
      ]
    },
    "647": {
      "js": [
        {
          "file": "assets/js/5e95c892.c7dfe9eb.js",
          "hash": "eaeee8a6d10409e4",
          "publicPath": "/ur/assets/js/5e95c892.c7dfe9eb.js"
        }
      ]
    },
    "742": {
      "js": [
        {
          "file": "assets/js/aba21aa0.5222a56e.js",
          "hash": "fb9ee503941d0fb3",
          "publicPath": "/ur/assets/js/aba21aa0.5222a56e.js"
        }
      ]
    },
    "759": {
      "js": [
        {
          "file": "assets/js/349d9f3b.db73aa30.js",
          "hash": "bbeeabbc25c50241",
          "publicPath": "/ur/assets/js/349d9f3b.db73aa30.js"
        }
      ]
    },
    "782": {
      "js": [
        {
          "file": "assets/js/88884f83.7470b4dd.js",
          "hash": "0831f6ac90881e26",
          "publicPath": "/ur/assets/js/88884f83.7470b4dd.js"
        }
      ]
    },
    "792": {
      "js": [
        {
          "file": "assets/js/main.d86714fa.js",
          "hash": "5d64089330753a94",
          "publicPath": "/ur/assets/js/main.d86714fa.js"
        }
      ]
    },
    "869": {
      "js": [
        {
          "file": "assets/js/fe675a51.71cbc0db.js",
          "hash": "4fb8e6cf5979f8c4",
          "publicPath": "/ur/assets/js/fe675a51.71cbc0db.js"
        }
      ]
    },
    "897": {
      "js": [
        {
          "file": "assets/js/eebfa656.c77dcbcd.js",
          "hash": "c02de87d06b59314",
          "publicPath": "/ur/assets/js/eebfa656.c77dcbcd.js"
        }
      ]
    },
    "906": {
      "js": [
        {
          "file": "assets/js/e0d24761.6378c308.js",
          "hash": "814cff2a15261559",
          "publicPath": "/ur/assets/js/e0d24761.6378c308.js"
        }
      ]
    },
    "959": {
      "js": [
        {
          "file": "assets/js/c82c7672.5a94ab2d.js",
          "hash": "d9a6542a4a347562",
          "publicPath": "/ur/assets/js/c82c7672.5a94ab2d.js"
        }
      ]
    },
    "976": {
      "js": [
        {
          "file": "assets/js/0e384e19.96eef6f3.js",
          "hash": "b35ae592643dd862",
          "publicPath": "/ur/assets/js/0e384e19.96eef6f3.js"
        }
      ]
    }
  }
}